[
  {
    "_id": "669a541d3c5c5ed513b82dff",
    "name": "Family Biryani Meal",
    "description": "A family that eats together stays together! Serves 4 - 5 People Enjoy your family time with our irresistible range of Biryani’s and kababs. Choose from our Classic,Epic or Gen-Z Biryani and we will pack it up with a box of Kababs. Deal :- +Biryani rice (1.5 Kgs Cooked rice) +Biryani chicken ( 15 Pieces) +Chicken Kabab ( 15 Pieces) +Made to Order",
    "subname": "1.5 Kg cooked Biryani rice + 15 pieces cooked Biryani chicken + 15 pieces Kabab",
    "amount": 790,
    "offeramount": 999,
    "images": [
      "https://storage.googleapis.com/email-js-1a09b.appspot.com/localHeros/1713272313248-66690156",
      "https://storage.googleapis.com/email-js-1a09b.appspot.com/localHeros/1713852542262-742019666",
      "https://storage.googleapis.com/email-js-1a09b.appspot.com/localHeros/1713852542257-947743978"
    ],
    "color": "Red",
    "weight": "1.5 kg",
    "dimensions": "10x5x2 inches",
    "sku": "FB-1233455",
    "availability": "In Stock",
    "qty": 50,
    "isActive": true,
    "createdBy": "668fbb47fc97f2063a0132a3",
    "category": "65d885c1e5d7ac618080e397",
    "createdAt": "2024-02-26T05:58:34.774Z",
    "lang": "IND",
    "exta_add_item": "250",
    "options": true,
    "__v": 0,
    "is_type": "Veg",
  
    "itemIdArray": ["10542633", "10542634", "10542635", "10542644"],
    "itemObjectArray": [
      {
        "itemid": "10542633",
        "itemallowvariation": "0",
        "itemrank": "1",
        "item_categoryid": "77773",
        "item_ordertype": "1,2,3",
        "item_packingcharges": "60",
        "itemallowaddon": "1",
        "itemaddonbasedon": "0",
        "item_favorite": "0",
        "ignore_taxes": "0",
        "ignore_discounts": "0",
        "in_stock": "2",
        "cuisine": [],
        "variation_groupname": "",
        "variation": [],
        "addon": [
          {
            "addon_group_id": "11621",
            "addon_item_selection_min": "0",
            "addon_item_selection_max": "1"
          },
          {
            "addon_group_id": "11620",
            "addon_item_selection_min": "0",
            "addon_item_selection_max": "4"
          }
        ],
        "is_recommend": "0",
        "itemname": "Classic Mysore - Family Biryani Meal",
        "item_attributeid": "2",
        "itemdescription": "A family that eats together stays together! Serves 4 - 5 People Enjoy your family time with our irresistible range of biryani and kababs. Choose from our Classic,Epic, 65 Boneless or Hyderabadi biryani and we will pack it up with a box of Kababs. Deal :-  - Chicken Biryani rice ( 1.5 Kgs Cooked rice ) - Chicken Biryani meat ( 15 Pieces ) -Chicken Kabab ( 15 Pieces ) -Made to Order",
        "minimumpreparationtime": "",
        "price": "990.00",
        "active": "1",
        "item_image_url": "",
        "item_tax": "2532,2533",
        "tax_inclusive": false,
        "gst_type": "services"
      },
      {
        "itemid": "10542634",
        "itemallowvariation": "0",
        "itemrank": "1",
        "item_categoryid": "77773",
        "item_ordertype": "1,2,3",
        "item_packingcharges": "60",
        "itemallowaddon": "1",
        "itemaddonbasedon": "0",
        "item_favorite": "0",
        "ignore_taxes": "0",
        "ignore_discounts": "0",
        "in_stock": "2",
        "cuisine": [],
        "variation_groupname": "",
        "variation": [],
        "addon": [
          {
            "addon_group_id": "11621",
            "addon_item_selection_min": "0",
            "addon_item_selection_max": "1"
          },
          {
            "addon_group_id": "11620",
            "addon_item_selection_min": "0",
            "addon_item_selection_max": "4"
          }
        ],
        "is_recommend": "0",
        "itemname": "Epic Bangalore - Family Biryani Meal",
        "item_attributeid": "2",
        "itemdescription": "A family that eats together stays together! Serves 4 - 5 People Enjoy your family time with our irresistible range of biryani and kababs. Choose from our Classic,Epic, 65 Boneless or Hyderabadi biryani and we will pack it up with a box of Kababs. Deal :-  - Chicken Biryani rice ( 1.5 Kgs Cooked rice ) - Chicken Biryani meat ( 15 Pieces ) -Chicken Kabab ( 15 Pieces ) -Made to Order",
        "minimumpreparationtime": "",
        "price": "990.00",
        "active": "1",
        "item_image_url": "",
        "item_tax": "2532,2533",
        "tax_inclusive": false,
        "gst_type": "services"
      },
      {
        "itemid": "10542635",
        "itemallowvariation": "0",
        "itemrank": "1",
        "item_categoryid": "77773",
        "item_ordertype": "1,2,3",
        "item_packingcharges": "60",
        "itemallowaddon": "1",
        "itemaddonbasedon": "0",
        "item_favorite": "0",
        "ignore_taxes": "0",
        "ignore_discounts": "0",
        "in_stock": "2",
        "cuisine": [],
        "variation_groupname": "",
        "variation": [],
        "addon": [
          {
            "addon_group_id": "11621",
            "addon_item_selection_min": "0",
            "addon_item_selection_max": "1"
          },
          {
            "addon_group_id": "11620",
            "addon_item_selection_min": "0",
            "addon_item_selection_max": "4"
          }
        ],
        "is_recommend": "0",
        "itemname": "65 Boneless - Family Biryani Meal",
        "item_attributeid": "2",
        "itemdescription": "A family that eats together stays together! Serves 4 - 5 People Enjoy your family time with our irresistible range of biryani and kababs. Choose from our Classic,Epic, 65 Boneless or Hyderabadi biryani and we will pack it up with a box of Kababs. Deal :-  - Chicken Biryani rice ( 1.5 Kgs Cooked rice ) - Chicken Biryani meat ( 15 Pieces ) -Chicken Kabab ( 15 Pieces ) -Made to Order",
        "minimumpreparationtime": "",
        "price": "990.00",
        "active": "1",
        "item_image_url": "",
        "item_tax": "2532,2533",
        "tax_inclusive": false,
        "gst_type": "services"
      },
      {
        "itemid": "10542644",
        "itemallowvariation": "0",
        "itemrank": "1",
        "item_categoryid": "77773",
        "item_ordertype": "1,2,3",
        "item_packingcharges": "60",
        "itemallowaddon": "1",
        "itemaddonbasedon": "0",
        "item_favorite": "0",
        "ignore_taxes": "0",
        "ignore_discounts": "0",
        "in_stock": "2",
        "cuisine": [],
        "variation_groupname": "",
        "variation": [],
        "addon": [
          {
            "addon_group_id": "11621",
            "addon_item_selection_min": "0",
            "addon_item_selection_max": "1"
          },
          {
            "addon_group_id": "11620",
            "addon_item_selection_min": "0",
            "addon_item_selection_max": "4"
          }
        ],
        "is_recommend": "0",
        "itemname": "Hyderabadi Biryani Family Pack",
        "item_attributeid": "2",
        "itemdescription": "A family that eats together stays together! Serves 4 - 5 People Enjoy your family time with our irresistible range of biryani and kababs. Choose from our Classic,Epic, 65 Boneless or Hyderabadi biryani and we will pack it up with a box of Kababs. Deal :-  - Chicken Biryani rice ( 1.5 Kgs Cooked rice ) - Chicken Biryani meat ( 15 Pieces ) -Chicken Kabab ( 15 Pieces ) -Made to Order",
        "minimumpreparationtime": "",
        "price": "990.00",
        "active": "1",
        "item_image_url": "",
        "item_tax": "2532,2533",
        "tax_inclusive": false,
        "gst_type": "goods"
      }
    ]
  },
  {
    "_id": "669a541d3c5c5ed513b82dfd",
    "name": "Classic Mysore Biryani",
    "description": "Our Classic Mysore Biryani is an all time favourite across all age groups and classes! Mysore style biriyaani is truly a delight to your taste buds with rich flavours and yet subtle. Its time to experience this wonderful curation handcrafted by our biriyaani heroes with premium ingredients like cold pressed oil, 18 months aged rice, organic vegetables, freshly pound secret masala and ofcourse the traditional style of cooking.",
    "subname": "450 gms(300gms Cooked Rice + 150gms Meat)",
    "amount": 149,
    "offeramount": 199,
    "images": [
      "https://storage.googleapis.com/email-js-1a09b.appspot.com/localHeros/1713434863898-757327946"
    ],
    "color": "Red",
    "weight": "1.5 kg",
    "dimensions": "10x5x2 inches",
    "sku": "BOX123",
    "availability": "In Stock",
    "qty": 5,
    "isActive": true,
    "createdBy": "668fbb47fc97f2063a0132a3",
    "category": "65d8859be5d7ac618080e395",
    "createdAt": "2024-02-26T05:54:25.860Z",
    "lang": "IND",
    "exta_add_item": "250",
    "options": false,
    "__v": 0,
    "is_type": "Veg",
    "itemid": "10542627",
    "itemObject": {
      "itemid": "10542627",
      "itemallowvariation": "0",
      "itemrank": "1",
      "item_categoryid": "77770",
      "item_ordertype": "1,2,3",
      "item_packingcharges": "15",
      "itemallowaddon": "1",
      "itemaddonbasedon": "0",
      "item_favorite": "0",
      "ignore_taxes": "0",
      "ignore_discounts": "0",
      "in_stock": "2",
      "cuisine": [],
      "variation_groupname": "",
      "variation": [],
      "addon": [
        {
          "addon_group_id": "11619",
          "addon_item_selection_min": "0",
          "addon_item_selection_max": "1"
        },
        {
          "addon_group_id": "11620",
          "addon_item_selection_min": "0",
          "addon_item_selection_max": "4"
        }
      ],
      "is_recommend": "0",
      "itemname": "Classic Mysore Biryani",
      "item_attributeid": "2",
      "itemdescription": "Our Classic Mysore biryani is an all time favourite across all age groups and classes! Mysore style biryani is truly a delight to your taste buds with rich flavours and yet subtle. It's time to experience this wonderful curation handcrafted by our biryani heroes with premium ingredients like cold pressed oil, 18 months aged rice, organic vegetables, freshly pound secret masala and of course the traditional style of cooking.",
      "minimumpreparationtime": "",
      "price": "199.00",
      "active": "1",
      "item_image_url": "",
      "item_tax": "2532,2533",
      "tax_inclusive": false,
      "gst_type": "services"
    }
  },
  {
    "_id": "669a541d3c5c5ed513b82dfe",
    "name": "Epic Bangalore Biryani",
    "description": "Experience the bangalore style Biryani which was cherised by the old bangaloreans from the old times! Dum cooked to perfection, a time honored tradition, handcrafted by our biriyaani heroes ensuring each fluffy grain of rice is infused with aromatic spices. We at local heros make this biriyaani tastier and healthier by using finest premium ingredients like cold-pressed groundnut oil, 18-month aged Seeraga Samba rice, organic vegetables, and freshly pounded masala.",
    "subname": "450 gms(300gms Cooked Rice + 150gms Meat)",
    "amount": 149,
    "offeramount": 199,
    "images": [
      "https://storage.googleapis.com/email-js-1a09b.appspot.com/localHeros/1713266647721-182678375"
    ],
    "color": "Red",
    "weight": "1.5 kg",
    "dimensions": "10x5x2 inches",
    "sku": "ABC123",
    "availability": "In Stock",
    "qty": 5,
    "isActive": true,
    "createdBy": "668fbb47fc97f2063a0132a3",
    "category": "65d8859be5d7ac618080e395",
    "createdAt": "2024-02-26T05:58:04.645Z",
    "lang": "IND",
    "exta_add_item": "250",
    "options": false,
    "__v": 0,
    "is_type": "Veg",
    "itemid": "10542639",
    "itemObject": {
      "itemid": "10542639",
      "itemallowvariation": "0",
      "itemrank": "1",
      "item_categoryid": "77770",
      "item_ordertype": "1,2,3",
      "item_packingcharges": "15",
      "itemallowaddon": "1",
      "itemaddonbasedon": "0",
      "item_favorite": "0",
      "ignore_taxes": "0",
      "ignore_discounts": "0",
      "in_stock": "2",
      "cuisine": [],
      "variation_groupname": "",
      "variation": [],
      "addon": [
        {
          "addon_group_id": "11619",
          "addon_item_selection_min": "0",
          "addon_item_selection_max": "1"
        },
        {
          "addon_group_id": "11620",
          "addon_item_selection_min": "0",
          "addon_item_selection_max": "4"
        }
      ],
      "is_recommend": "0",
      "itemname": "Epic Bangalore Biryani",
      "item_attributeid": "2",
      "itemdescription": "Experience the bangalore style Biryani which was cherished by the old bangaloreans from the old times! Dum cooked to perfection, a time honored tradition, handcrafted  by our biryani heroes ensuring each fluffy grain of rice is infused with aromatic spices. We at local heros make this biryani tastier and healthier by using finest premium ingredients like cold-pressed groundnut oil, 18-month aged Seeraga Samba rice, organic vegetables, and  freshly pounded masala.",
      "minimumpreparationtime": "",
      "price": "199.00",
      "active": "1",
      "item_image_url": "",
      "item_tax": "2532,2533",
      "tax_inclusive": false,
      "gst_type": "services"
    }
  },
  {
    "_id": "669a541d3c5c5ed513b82e05",
    "name": "250 Gms - 8 Pieces",
    "description": "Deep-fried to juicy perfection! Our Indian style kabab is always an evergreen choice of kabab. Enjoy them as an appetiser,or main course with rice or greens or pair them with drinks or your favourite Biriyaani - these versatile Kababs are a delicious addition to any meal.",
    "subname": "8 pieces",
    "amount": 149,
    "offeramount": 250,
    "images": [
      "https://storage.googleapis.com/email-js-1a09b.appspot.com/localHeros/1713270584112-432473079"
    ],
    "color": "RED",
    "weight": "500 gms",
    "dimensions": "10x15",
    "sku": "KB-1234",
    "availability": "In Stock",
    "qty": 100,
    "isActive": true,
    "createdBy": "661e3cc86ea4ac0272d813e9",
    "category": "661133469875ecd47c09fe74",
    "createdAt": "2024-04-06T11:36:28.568Z",
    "lang": "IND",
    "exta_add_item": "100",
    "options": false,
    "__v": 0,
    "itemid": "10542630",
    "itemObject": {
      "itemid": "10542630",
      "itemallowvariation": "0",
      "itemrank": "1",
      "item_categoryid": "77772",
      "item_ordertype": "1,2,3",
      "item_packingcharges": "5",
      "itemallowaddon": "0",
      "itemaddonbasedon": "0",
      "item_favorite": "0",
      "ignore_taxes": "0",
      "ignore_discounts": "0",
      "in_stock": "2",
      "cuisine": [],
      "variation_groupname": "",
      "variation": [],
      "addon": [],
      "is_recommend": "0",
      "itemname": "250 Gms - 8 Pieces",
      "item_attributeid": "2",
      "itemdescription": "Deep-fried to juicy perfection! Our Indian style kabab is always an evergreen choice of kabab. Enjoy them as an appetiser,or main course with rice or greens or pair them with drinks or your favourite Biriyaani - these versatile Kababs are a delicious addition to any meal.",
      "minimumpreparationtime": "",
      "price": "179.00",
      "active": "1",
      "item_image_url": "",
      "item_tax": "2532,2533",
      "tax_inclusive": false,
      "gst_type": "services"
    }
  },
  {
    "_id": "669a541d3c5c5ed513b82e00",
    "name": "Party Biryani Meal",
    "description": "No party can be completed without Biryani and Kababs! Serves 8 - 10 people Make your party time more delightful with our irresistible range of biriyaani’s and Kababs. Choose from our Classic,Epic and we will pack it up with a large box of Kababs. Deal: +Biryani Rice (3 Kgs cooked rice ) +Biryani chicken ( 30 Pieces ) +Kabab ( 32 Pieces ) +Made to Order",
    "subname": "3 Kg cooked Biryani rice + 30 pieces cooked Biryani chicken + 32 pieces Kabab",
    "amount": 1490,
    "offeramount": 1799,
    "images": [
      "https://storage.googleapis.com/email-js-1a09b.appspot.com/localHeros/1713272340064-351037068",
      "https://storage.googleapis.com/email-js-1a09b.appspot.com/localHeros/1713852287767-888611957",
      "https://storage.googleapis.com/email-js-1a09b.appspot.com/localHeros/1713852287761-111157282"
    ],
    "color": "RED",
    "weight": "128",
    "dimensions": "12 x 32",
    "sku": "PB-1233445",
    "availability": "In Stock",
    "qty": 100,
    "isActive": true,
    "createdBy": "661e3cc86ea4ac0272d813e9",
    "category": "66975897bf917350f1346836",
    "createdAt": "2024-02-28T08:37:07.654Z",
    "lang": "IND",
    "exta_add_item": "250",
    "options": true,
    "__v": 0,
    "itemIdArray": ["10542636", "10542637", "10542638", "10542645"],
    "itemObjectArray": [
      {
        "itemid": "10542636",
        "itemallowvariation": "0",
        "itemrank": "1",
        "item_categoryid": "77774",
        "item_ordertype": "1,2,3",
        "item_packingcharges": "90",
        "itemallowaddon": "1",
        "itemaddonbasedon": "0",
        "item_favorite": "0",
        "ignore_taxes": "0",
        "ignore_discounts": "0",
        "in_stock": "2",
        "cuisine": [],
        "variation_groupname": "",
        "variation": [],
        "addon": [
          {
            "addon_group_id": "11620",
            "addon_item_selection_min": "0",
            "addon_item_selection_max": "4"
          },
          {
            "addon_group_id": "11622",
            "addon_item_selection_min": "0",
            "addon_item_selection_max": "1"
          }
        ],
        "is_recommend": "0",
        "itemname": "Classic Mysore - Party Biryani Meal",
        "item_attributeid": "2",
        "itemdescription": "No party can be completed without biryani and Kababs! Serves 8 - 10 people Make your party time more delightful with our irresistible range of biryani’s and Kababs. Choose from our Classic,Epic, 65 Boneless or Hyderabadi biryani and we will pack it up with a large box of Kababs. Deal: - Chicken Biryani Rice (3 Kgs cooked rice ) -Chicken Biryani meat ( 30 Pieces ) -Kabab ( 32 Pieces ) -Made to Order",
        "minimumpreparationtime": "",
        "price": "1790.00",
        "active": "1",
        "item_image_url": "",
        "item_tax": "2532,2533",
        "tax_inclusive": false,
        "gst_type": "services"
      },
      {
        "itemid": "10542637",
        "itemallowvariation": "0",
        "itemrank": "1",
        "item_categoryid": "77774",
        "item_ordertype": "1,2,3",
        "item_packingcharges": "90",
        "itemallowaddon": "1",
        "itemaddonbasedon": "0",
        "item_favorite": "0",
        "ignore_taxes": "0",
        "ignore_discounts": "0",
        "in_stock": "2",
        "cuisine": [],
        "variation_groupname": "",
        "variation": [],
        "addon": [
          {
            "addon_group_id": "11620",
            "addon_item_selection_min": "0",
            "addon_item_selection_max": "4"
          },
          {
            "addon_group_id": "11622",
            "addon_item_selection_min": "0",
            "addon_item_selection_max": "1"
          }
        ],
        "is_recommend": "0",
        "itemname": "Epic Bangalore - Party Biryani Meal",
        "item_attributeid": "2",
        "itemdescription": "No party can be completed without biryani and Kababs! Serves 8 - 10 people Make your party time more delightful with our irresistible range of biryani’s and Kababs. Choose from our Classic,Epic, 65 Boneless or Hyderabadi biryani and we will pack it up with a large box of Kababs. Deal: - Chicken Biryani Rice (3 Kgs cooked rice ) -Chicken Biryani meat ( 30 Pieces ) -Kabab ( 32 Pieces ) -Made to Order",
        "minimumpreparationtime": "",
        "price": "1790.00",
        "active": "1",
        "item_image_url": "",
        "item_tax": "2532,2533",
        "tax_inclusive": false,
        "gst_type": "services"
      },
      {
        "itemid": "10542638",
        "itemallowvariation": "0",
        "itemrank": "1",
        "item_categoryid": "77774",
        "item_ordertype": "1,2,3",
        "item_packingcharges": "90",
        "itemallowaddon": "1",
        "itemaddonbasedon": "0",
        "item_favorite": "0",
        "ignore_taxes": "0",
        "ignore_discounts": "0",
        "in_stock": "2",
        "cuisine": [],
        "variation_groupname": "",
        "variation": [],
        "addon": [
          {
            "addon_group_id": "11620",
            "addon_item_selection_min": "0",
            "addon_item_selection_max": "4"
          },
          {
            "addon_group_id": "11622",
            "addon_item_selection_min": "0",
            "addon_item_selection_max": "1"
          }
        ],
        "is_recommend": "0",
        "itemname": "65 Boneless - Party Biryani Meal",
        "item_attributeid": "2",
        "itemdescription": "No party can be completed without biryani and Kababs! Serves 8 - 10 people Make your party time more delightful with our irresistible range of biryani’s and Kababs. Choose from our Classic,Epic, 65 Boneless or Hyderabadi biryani and we will pack it up with a large box of Kababs. Deal: - Chicken Biryani Rice (3 Kgs cooked rice ) -Chicken Biryani meat ( 30 Pieces ) -Kabab ( 32 Pieces ) -Made to Order",
        "minimumpreparationtime": "",
        "price": "1790.00",
        "active": "1",
        "item_image_url": "",
        "item_tax": "2532,2533",
        "tax_inclusive": false,
        "gst_type": "services"
      },
      {
        "itemid": "10542645",
        "itemallowvariation": "0",
        "itemrank": "1",
        "item_categoryid": "77774",
        "item_ordertype": "1,2,3",
        "item_packingcharges": "90",
        "itemallowaddon": "1",
        "itemaddonbasedon": "0",
        "item_favorite": "0",
        "ignore_taxes": "0",
        "ignore_discounts": "0",
        "in_stock": "2",
        "cuisine": [],
        "variation_groupname": "",
        "variation": [],
        "addon": [
          {
            "addon_group_id": "11620",
            "addon_item_selection_min": "0",
            "addon_item_selection_max": "4"
          },
          {
            "addon_group_id": "11622",
            "addon_item_selection_min": "0",
            "addon_item_selection_max": "1"
          }
        ],
        "is_recommend": "0",
        "itemname": "Hyderabadi - Party Biyani Meal",
        "item_attributeid": "2",
        "itemdescription": "No party can be completed without biryani and Kababs! Serves 8 - 10 people Make your party time more delightful with our irresistible range of biryani’s and Kababs. Choose from our Classic,Epic, 65 Boneless or Hyderabadi biryani and we will pack it up with a large box of Kababs. Deal: - Chicken Biryani Rice (3 Kgs cooked rice ) -Chicken Biryani meat ( 30 Pieces ) -Kabab ( 32 Pieces ) -Made to Order",
        "minimumpreparationtime": "",
        "price": "1790.00",
        "active": "1",
        "item_image_url": "",
        "item_tax": "2532,2533",
        "tax_inclusive": false,
        "gst_type": "services"
      }
    ]
  },
  {
    "_id": "669a541d3c5c5ed513b82e02",
    "name": "Classic Mysore Biryani + Kabab",
    "description": "Ditch the decision fatigue - we've got your complete feast covered! Choose your favourite Biryani, from our range of Classic, Epic or Gen-Z and we will make it even more exciting by adding some Kababs to the box.",
    "subname": "450 gms(300gms Cooked Rice + 150gms Meat) + 120 gms Kabab",
    "amount": 249,
    "offeramount": 350,
    "images": [
      "https://storage.googleapis.com/email-js-1a09b.appspot.com/localHeros/1713266756855-32324212"
    ],
    "color": "RED",
    "weight": "500g",
    "dimensions": "10x15",
    "sku": "CM-11233444",
    "availability": "In Stock",
    "qty": 200,
    "isActive": true,
    "createdBy": "661d0fd31f4ad46ee3f44c7f",
    "category": "66112d909875ecd47c09fe32",
    "createdAt": "2024-04-06T11:17:37.608Z",
    "lang": "IND",
    "exta_add_item": "250",
    "options": false,
    "__v": 0,
    "itemid": "10542628",
    "itemObject": {
      "itemid": "10542628",
      "itemallowvariation": "0",
      "itemrank": "1",
      "item_categoryid": "77771",
      "item_ordertype": "1,2,3",
      "item_packingcharges": "15",
      "itemallowaddon": "1",
      "itemaddonbasedon": "0",
      "item_favorite": "0",
      "ignore_taxes": "0",
      "ignore_discounts": "0",
      "in_stock": "2",
      "cuisine": [],
      "variation_groupname": "",
      "variation": [],
      "addon": [
        {
          "addon_group_id": "11619",
          "addon_item_selection_min": "0",
          "addon_item_selection_max": "1"
        },
        {
          "addon_group_id": "11621",
          "addon_item_selection_min": "0",
          "addon_item_selection_max": "1"
        },
        {
          "addon_group_id": "11620",
          "addon_item_selection_min": "0",
          "addon_item_selection_max": "4"
        }
      ],
      "is_recommend": "0",
      "itemname": "Classic Mysore Biryani + Kabab",
      "item_attributeid": "2",
      "itemdescription": "Ditch the decision fatigue - we've got your complete feast covered!   Choose your favourite Biriyaani, from our range of Cassic Mysore, Epic Bangalore, Hyderabadi or Chicken 65 Biryani and we will make it even more exciting by adding some Kababs to the box.",
      "minimumpreparationtime": "",
      "price": "299.00",
      "active": "1",
      "item_image_url": "",
      "item_tax": "2532,2533",
      "tax_inclusive": false,
      "gst_type": "services"
    }
  },
  {
    "_id": "669a541d3c5c5ed513b82e04",
    "name": "Epic Mysore Biryani + Kabab",
    "description": "Ditch the decision fatigue - we've got your complete feast covered! Choose your favourite Biryani, from our range of Classic, Epic or Gen-Z and we will make it even more exciting by adding some Kababs to the box.",
    "subname": "450 gms(300gms Cooked Rice + 150gms Meat) + 120 gms Kabab",
    "amount": 249,
    "offeramount": 350,
    "images": [
      "https://storage.googleapis.com/email-js-1a09b.appspot.com/localHeros/1713266801722-650545419"
    ],
    "color": "RED",
    "weight": "1000g",
    "dimensions": "10x15",
    "sku": "EM-11233442",
    "availability": "In Stock",
    "qty": 200,
    "isActive": true,
    "createdBy": "661d0fd31f4ad46ee3f44c7f",
    "category": "66112d909875ecd47c09fe32",
    "createdAt": "2024-04-06T11:21:53.940Z",
    "lang": "IND",
    "exta_add_item": "250",
    "options": false,
    "__v": 0,
    "itemid": "10542641",
    "itemObject": {
      "itemid": "10542641",
      "itemallowvariation": "0",
      "itemrank": "1",
      "item_categoryid": "77771",
      "item_ordertype": "1,2,3",
      "item_packingcharges": "15",
      "itemallowaddon": "1",
      "itemaddonbasedon": "0",
      "item_favorite": "0",
      "ignore_taxes": "0",
      "ignore_discounts": "0",
      "in_stock": "2",
      "cuisine": [],
      "variation_groupname": "",
      "variation": [],
      "addon": [
        {
          "addon_group_id": "11619",
          "addon_item_selection_min": "0",
          "addon_item_selection_max": "1"
        },
        {
          "addon_group_id": "11621",
          "addon_item_selection_min": "0",
          "addon_item_selection_max": "1"
        },
        {
          "addon_group_id": "11620",
          "addon_item_selection_min": "0",
          "addon_item_selection_max": "4"
        }
      ],
      "is_recommend": "0",
      "itemname": "Epic Bangalore Biryani+ Kabab",
      "item_attributeid": "2",
      "itemdescription": "Ditch the decision fatigue - we've got your complete feast covered!   Choose your favourite Biriyaani, from our range of Cassic Mysore, Epic Bangalore, Hyderabadi or Chicken 65 Biryani and we will make it even more exciting by adding some Kababs to the box.",
      "minimumpreparationtime": "",
      "price": "299.00",
      "active": "1",
      "item_image_url": "",
      "item_tax": "2532,2533",
      "tax_inclusive": false,
      "gst_type": "services"
    }
  },
  {
    "_id": "669a541d3c5c5ed513b82e07",
    "name": "Dhamaka ( Serves 6 - 8 )",
    "description": "Deep-fried to juicy perfection! Our Indian style kabab is always an evergreen choice of kabab. Enjoy them as an appetiser,or main course with rice or greens or pair them with drinks or your favourite Biriyaani - these versatile Kababs are a delicious addition to any meal.",
    "subname": "32 Pieces",
    "amount": 495,
    "offeramount": 700,
    "images": [
      "https://storage.googleapis.com/email-js-1a09b.appspot.com/localHeros/1713270605034-707089806"
    ],
    "color": "RED",
    "weight": "1000 gms",
    "dimensions": "10x15",
    "sku": "KB-1236",
    "availability": "In Stock",
    "qty": 100,
    "isActive": true,
    "createdBy": "661e3cc86ea4ac0272d813e9",
    "category": "661133469875ecd47c09fe74",
    "createdAt": "2024-04-06T11:39:17.079Z",
    "lang": "IND",
    "exta_add_item": "250",
    "options": false,
    "__v": 0,
    "itemid": "10542632",
    "itemObject":
    {
        "itemid": "10542632",
        "itemallowvariation": "0",
        "itemrank": "1",
        "item_categoryid": "77772",
        "item_ordertype": "1,2,3",
        "item_packingcharges": "15",
        "itemallowaddon": "0",
        "itemaddonbasedon": "0",
        "item_favorite": "0",
        "ignore_taxes": "0",
        "ignore_discounts": "0",
        "in_stock": "2",
        "cuisine": [],
        "variation_groupname": "",
        "variation": [],
        "addon": [],
        "is_recommend": "0",
        "itemname": "1 Kg - 32 Piece",
        "item_attributeid": "2",
        "itemdescription": "Deep-fried to juicy perfection! Our Indian style kabab is always an evergreen choice of kabab. Enjoy them as an appetiser,or main course with rice or greens or pair them with drinks or your favourite Biriyaani - these versatile Kababs are a delicious addition to any meal.",
        "minimumpreparationtime": "",
        "price": "649.00",
        "active": "1",
        "item_image_url": "",
        "item_tax": "2532,2533",
        "tax_inclusive": false,
        "gst_type": "services"
    }
  },
  {
    "_id": "669a541d3c5c5ed513b82e01",
    "name": "65 Boneless Biryani",
    "description": "This dum-cooked Biryani feOur is a modern twist on the classic, perfect for busy lifestyles! This dum-cooked biriyaani features juicy, boneless \"special chicken\" nestled amidst fluffy seeraga samba rice with fragrant spices that will excite your taste buds. Its time to experience this wonderful curation handcrafted by our Biryani heros with premium ingredients like cold pressed oil, 18 months aged rice, organic vegetables, freshly pound secret masala and of course the traditional style of cooking.atures juicy, boneless \"special chicken\" nestled amidst fluffy geeeraga samba rice. Fragrant spices will excite your taste buds and the skip-the-bone approach lets you savour the flavour without the hassle. Its time to experience this wonderful curation handcrafted by our biriyaani heros with premium ingredients like cold pressed oil, 18 months aged rice, organic vegetables, freshly pound secret masala and ofcourse the traditional style of cooking.",
    "subname": "450 gms(300gms Cooked Rice + 150gms Meat)",
    "amount": 149,
    "offeramount": 199,
    "images": [
      "https://storage.googleapis.com/email-js-1a09b.appspot.com/localHeros/1713270533201-909090803"
    ],
    "color": "RED",
    "weight": "500g",
    "dimensions": "10x15",
    "sku": "EP-11233444",
    "availability": "In Stock",
    "qty": 200,
    "isActive": true,
    "createdBy": "661d0fd31f4ad46ee3f44c7f",
    "category": "65d8859be5d7ac618080e395",
    "createdAt": "2024-04-06T11:14:28.409Z",
    "lang": "IND",
    "exta_add_item": "250",
    "options": false,
    "__v": 0,
    "itemid": "10542640",
    "itemObject": {
      "itemid": "10542640",
      "itemallowvariation": "0",
      "itemrank": "1",
      "item_categoryid": "77770",
      "item_ordertype": "1,2,3",
      "item_packingcharges": "15",
      "itemallowaddon": "1",
      "itemaddonbasedon": "0",
      "item_favorite": "0",
      "ignore_taxes": "0",
      "ignore_discounts": "0",
      "in_stock": "2",
      "cuisine": [],
      "variation_groupname": "",
      "variation": [],
      "addon": [
        {
          "addon_group_id": "11619",
          "addon_item_selection_min": "0",
          "addon_item_selection_max": "1"
        },
        {
          "addon_group_id": "11620",
          "addon_item_selection_min": "0",
          "addon_item_selection_max": "4"
        }
      ],
      "is_recommend": "0",
      "itemname": "65 Boneless Biryani",
      "item_attributeid": "2",
      "itemdescription": "Our Chicken 65 Boneless Biryani is a modern twist on the classic, perfect for busy lifestyles!  This dum-cooked biryani features juicy, boneless \"special chicken\" nestled amidst fluffy seeraga samba rice with fragrant spices that will excite your taste buds. It's time to experience this wonderful curation handcrafted by our biryani heros with premium ingredients like cold pressed oil, organic vegetables, freshly pound secret masala and of course the traditional style of cooking.",
      "minimumpreparationtime": "",
      "price": "199.00",
      "active": "1",
      "item_image_url": "",
      "item_tax": "2532,2533",
      "tax_inclusive": false,
      "gst_type": "services"
    }
  },
  {
    "_id": "669a541d3c5c5ed513b82e06",
    "name": "Pataka ( Serves 3-4 )",
    "description": "Deep-fried to juicy perfection! Our Indian style kabab is always an evergreen choice of kabab. Enjoy them as an appetiser,or main course with rice or greens or pair them with drinks or your favourite Biriyaani - these versatile Kababs are a delicious addition to any meal.",
    "subname": "16 Pieces",
    "amount": 275,
    "offeramount": 350,
    "images": [
      "https://storage.googleapis.com/email-js-1a09b.appspot.com/localHeros/1713270623833-883913782"
    ],
    "color": "RED",
    "weight": "500 gms",
    "dimensions": "10x15",
    "sku": "KB-1235",
    "availability": "In Stock",
    "qty": 100,
    "isActive": true,
    "createdBy": "661e3cc86ea4ac0272d813e9",
    "category": "661133469875ecd47c09fe74",
    "createdAt": "2024-04-06T11:38:00.428Z",
    "lang": "IND",
    "exta_add_item": "250",
    "options": false,
    "__v": 0,
    "itemid": "10542631",
    "itemObject": {
      "itemid": "10542631",
      "itemallowvariation": "0",
      "itemrank": "1",
      "item_categoryid": "77772",
      "item_ordertype": "1,2,3",
      "item_packingcharges": "10",
      "itemallowaddon": "0",
      "itemaddonbasedon": "0",
      "item_favorite": "0",
      "ignore_taxes": "0",
      "ignore_discounts": "0",
      "in_stock": "2",
      "cuisine": [],
      "variation_groupname": "",
      "variation": [],
      "addon": [],
      "is_recommend": "0",
      "itemname": "500 Gms - 16 Piece",
      "item_attributeid": "2",
      "itemdescription": "Deep-fried to juicy perfection! Our Indian style kabab is always an evergreen choice of kabab. Enjoy them as an appetiser,or main course with rice or greens or pair them with drinks or",
      "minimumpreparationtime": "",
      "price": "349.00",
      "active": "1",
      "item_image_url": "",
      "item_tax": "2532,2533",
      "tax_inclusive": false,
      "gst_type": "services"
    }
  },
  {
    "_id": "669a541d3c5c5ed513b82e03",
    "name": "65 Boneless Biryani + Kabab ",
    "description": "Ditch the decision fatigue - we've got your complete feast covered! Choose your favourite Biryani, from our range of Classic, Epic or Gen-Z and we will make it even more exciting by adding some Kababs to the box. ",
    "subname": "450 gms(300gms Cooked Rice + 150gms Meat) + 120 gms Kabab",
    "amount": 249,
    "offeramount": 350,
    "images": [
      "https://storage.googleapis.com/email-js-1a09b.appspot.com/localHeros/1713266781106-175524478"
    ],
    "color": "RED",
    "weight": "1000g",
    "dimensions": "10x15",
    "sku": "GM-11233444",
    "availability": "In Stock",
    "qty": 200,
    "isActive": true,
    "createdBy": "661d0fd31f4ad46ee3f44c7f",
    "category": "66112d909875ecd47c09fe32",
    "createdAt": "2024-04-06T11:20:01.919Z",
    "lang": "IND",
    "exta_add_item": "250",
    "options": false,
    "__v": 0,
    "itemid": "10542629",
    "itemObject": {
      "itemid": "10542629",
      "itemallowvariation": "0",
      "itemrank": "1",
      "item_categoryid": "77771",
      "item_ordertype": "1,2,3",
      "item_packingcharges": "15",
      "itemallowaddon": "1",
      "itemaddonbasedon": "0",
      "item_favorite": "0",
      "ignore_taxes": "0",
      "ignore_discounts": "0",
      "in_stock": "2",
      "cuisine": [],
      "variation_groupname": "",
      "variation": [],
      "addon": [
        {
          "addon_group_id": "11619",
          "addon_item_selection_min": "0",
          "addon_item_selection_max": "1"
        },
        {
          "addon_group_id": "11621",
          "addon_item_selection_min": "0",
          "addon_item_selection_max": "1"
        },
        {
          "addon_group_id": "11620",
          "addon_item_selection_min": "0",
          "addon_item_selection_max": "4"
        }
      ],
      "is_recommend": "0",
      "itemname": "65 Boneless Biryani + Kabab",
      "item_attributeid": "2",
      "itemdescription": "Ditch the decision fatigue - we've got your complete feast covered!   Choose your favourite Biriyaani, from our range of Cassic Mysore, Epic Bangalore, Hyderabadi or Chicken 65 Biryani and we will make it even more exciting by adding some Kababs to the box.",
      "minimumpreparationtime": "",
      "price": "299.00",
      "active": "1",
      "item_image_url": "",
      "item_tax": "2532,2533",
      "tax_inclusive": false,
      "gst_type": "services"
    }
  }
]
